{
  "resourceType": "Bundle",
  "type": "transaction",
  "entry": [
    {
      "fullUrl": "Group/0",
      "resource": {
        "resourceType": "Group",
        "id": "0",
        "actual": true,
        "type": "person",
        "name": "Empty #1"
      },
      "request": {
        "method": "POST",
        "url": "Group"
      }
    },
    {
      "fullUrl": "Group/1",
      "resource": {
        "resourceType": "Group",
        "id": "1",
        "actual": true,
        "type": "animal",
        "name": "Empty #2"
      },
      "request": {
        "method": "POST",
        "url": "Group"
      }
    },
    {
      "fullUrl": "Group/2",
      "resource": {
        "resourceType": "Group",
        "id": "2",
        "actual": true,
        "type": "person",
        "name": "Organization Managed #1",
        "managingEntity": {
          "reference": "Organization?identifier=e6c5d179-370a-3659-9ce6-3d09da3c3ad0"
        },
        "member": [ {
          "entity": {
            "reference": "Patient?identifier=678f72e9-9de7-59d5-37ce-13a92d481dfe"
          }
        } ]
      },
      "request": {
        "method": "POST",
        "url": "Group"
      }
    },
    {
      "fullUrl": "Group/3",
      "resource": {
        "resourceType": "Group",
        "id": "3",
        "actual": true,
        "type": "person",
        "name": "Practitioner Managed #1",
        "managingEntity": {
          "reference": "Practitioner?identifier=9b7a19e8-ba4a-3308-aed3-008b19037396"
        },
        "member": [
          {
            "entity": {
              "reference": "Patient?identifier=678f72e9-9de7-59d5-37ce-13a92d481dfe"
            }
          },
          {
            "entity": {
              "reference": "Patient?identifier=b6fc7c1e-c9d4-50ff-6a41-650c78d713a0"
            }
        } ]
      },
      "request": {
        "method": "POST",
        "url": "Group"
      }
    },
    {
      "fullUrl": "Group/4",
      "resource": {
        "resourceType": "Group",
        "id": "4",
        "actual": true,
        "type": "person",
        "name": "Location-based",
        "characteristic": [ {
          "code": {
            "coding": [ {
              "system": "http://argonautproject.org/patient-lists/CodeSystem/characteristics",
              "code": "at-location"
            } ]
          },
          "exclude": "false",
          "valueReference": {
            "reference": "Location?identifier=5f0a03d6-92b8-6ec2-cdd2-893281c43776"
          }
        } ],
        "member": [ {
          "entity": {
            "reference": "Patient?identifier=678f72e9-9de7-59d5-37ce-13a92d481dfe"
          }
        } ]
      },
      "request": {
        "method": "POST",
        "url": "Group"
      }
    },
    {
      "fullUrl": "Group/5",
      "resource": {
        "resourceType": "Group",
        "id": "5",
        "actual": true,
        "type": "person",
        "name": "Care Team List #1",
        "characteristic": [ {
          "code": {
            "coding": [ {
              "system": "http://argonautproject.org/patient-lists/CodeSystem/characteristics",
              "code": "attributed-to-care-team"
            } ]
          },
          "exclude": "false",
          "valueReference": {
            "reference": "CareTeam?identifier=155c6d2f-dfe8-9587-6caa-6dff329246ea"
          }
        } ],
        "member": [ {
          "entity": {
            "reference": "Patient?identifier=678f72e9-9de7-59d5-37ce-13a92d481dfe"
          }
        } ]
      },
      "request": {
        "method": "POST",
        "url": "Group"
      }
    }
  ]
}
